setup.cfg
setup.py
tempMail/__init__.py
tempMail/example.py
tempMail/tempMail.py
tempMail.egg-info/PKG-INFO
tempMail.egg-info/SOURCES.txt
tempMail.egg-info/dependency_links.txt
tempMail.egg-info/requires.txt
tempMail.egg-info/top_level.txt