Metadata-Version: 1.0
Name: tempMail
Version: 3.0
Summary: Module to generate an temporary e-mail
Home-page: https://github.com/mthbernardes/tempMail
Author: Matheus Bernardes
Author-email: mthbernardes@gmail.com
License: MIT License
Keywords: email temporary
Platform: UNKNOWN
